keras-gemini/__init__.py
keras-gemini/keras_gemini.py
keras-gemini/nlp_to_keras.py
tests/__init__.py
tests/test_keras_gemini.py
keras_gemini-0.1.2.dist-info/LICENSE
keras_gemini-0.1.2.dist-info/METADATA
keras_gemini-0.1.2.dist-info/WHEEL
keras_gemini-0.1.2.dist-info/top_level.txt
keras_gemini-0.1.2.dist-info/RECORD
