Metadata-Version: 2.1
Name: keras-gemini
Version: 0.1.2
Summary: A Python package that combines the power of Keras with Gemini for natural language-driven neural network building.
Home-page: https://github.com/wkambale/keras_gemini
Author: Wesley Kambale
Author-email: spartanwk@gmail.com
License: MIT
Platform: UNKNOWN
Classifier: Programming Language :: Python :: 3
Classifier: License :: OSI Approved :: MIT License
Classifier: Operating System :: OS Independent
Requires-Python: >=3.7
Requires-Dist: tensorflow
Requires-Dist: keras
Requires-Dist: gemini-python
Requires-Dist: nltk
